jdsh/__init__.py
jdsh/__main__.py
jdsh/cli.py
jdsh/client.py
jdsh/config.py
jdsh/tui.py
jdsh/utils.py
jdsh-1.0.1.dist-info/METADATA
jdsh-1.0.1.dist-info/WHEEL
jdsh-1.0.1.dist-info/entry_points.txt
jdsh-1.0.1.dist-info/licenses/LICENSE
jdsh-1.0.1.dist-info/RECORD
