Metadata-Version: 2.4
Name: jdsh
Version: 1.0.1
Summary: A CLI and TUI for JDownloader2
Project-URL: Homepage, https://github.com/al00x/jdsh
Author-email: Al00X <al00x@outlook.com>
License-File: LICENSE
Classifier: License :: OSI Approved :: MIT License
Classifier: Operating System :: OS Independent
Classifier: Programming Language :: Python :: 3
Requires-Python: >=3.8
Requires-Dist: myjdapi
Requires-Dist: rich
